{"Space": "63", "Episodic": "193", "Noir": "327", "Ensemble Cast": "105", "Primarily Adult Cast": "109", "Guns": "157", "Drugs": "489", "Amnesia": "240", "Martial Arts": "30", "Philosophy": "391", "Yakuza": "199", "Male Protagonist": "82", "Anti-Hero": "104", "Terrorism": "285", "Military": "34", "Work": "145", "Fugitive": "226", "Magic": "29", "Police": "40", "Conspiracy": "456", "Female Protagonist": "98", "Witch": "179", "Urban Fantasy": "321", "Shounen": "56", "American Football": "314", "Josei": "27", "Coming of Age": "102", "Love Triangle": "139", "College": "404", "Drawing": "118", "Cycling": "151", "Football": "148", "Cars": "10", "Seinen": "50", "Primarily Male Cast": "88", "CGI": "90", "Time Skip": "153", "Foreign": "198", "Ninja": "255", "Super Power": "66", "Cultivation": "326", "Primarily Child Cast": "446", "Pirates": "201", "Ships": "305", "Politics": "103", "Animals": "433", "Swordplay": "43", "Lost Civilization": "466", "Anachronism": "490", "Skeleton": "499", "Body Swapping": "154", "Samurai": "291", "Zombie": "152", "War": "111", "Tennis": "194", "School": "46", "Boxing": "169", "Post-Apocalyptic": "93", "Survival": "143", "Dystopian": "217", "Cyberpunk": "108", "Tragedy": "85", "Gangs": "106", "Vampire": "74", "Food": "142", "Parody": "39", "Historical": "25", "Robots": "175", "Kaiju": "276", "Super Robot": "159", "Tsundere": "164", "Real Robot": "160", "Mythology": "208", "Age Gap": "138", "Trains": "122", "Boys' Love": "75", "Tokusatsu": "513", "Meta": "144", "Nudity": "100", "Gore": "94", "Demons": "15", "Rape": "155", "Revenge": "252", "Artificial Intelligence": "517", "Espionage": "310", "Motorcycles": "173", "Virtual World": "112", "Isekai": "244", "Video Games": "308", "Primarily Female Cast": "86", "Gods": "253", "Shoujo": "53", "Reincarnation": "243", "Harem": "23", "Band": "110", "Aliens": "191", "Memory Manipulation": "365", "Multiple Personalities": "536", "Twins": "494", "Hikikomori": "282", "Battle Royale": "101", "Surreal Comedy": "281", "Cute Girls Doing Cute Things": "92", "4-koma": "206", "Teacher": "165", "Assassins": "322", "Aviation": "355", "Henshin": "99", "Yuri": "76", "Yandere": "163", "Space Opera": "162", "Wuxia": "303", "Steampunk": "95", "Crossdressing": "186", "Dragons": "224", "Fairy Tale": "400", "Family Life": "87", "Bullying": "171", "Delinquents": "395", "Reverse Harem": "123", "Alternate Universe": "146", "Slapstick": "83", "Mafia": "107", "Go": "443", "Ghost": "220", "Augmented Reality": "364", "Card Battle": "178", "Achronological Order": "156", "Youkai": "233", "Iyashikei": "81", "Slavery": "247", "Kids": "28", "Environmental": "342", "Rural": "250", "Time Manipulation": "96", "Basketball": "192", "Chibi": "324", "Idol": "115", "Crossover": "158", "Photography": "195", "Goblin": "480", "Writing": "394", "Gender Bending": "77", "Age Regression": "488", "Monster Girl": "259", "Nekomimi": "113", "Baseball": "149", "Afterlife": "147", "Bisexual": "294", "Golf": "532", "Educational": "140", "Classic Literature": "227", "Otaku Culture": "97", "School Club": "84", "Archery": "251", "Miko": "468", "Satire": "80", "Swimming": "150", "Triads": "214", "Cosplay": "328", "Maids": "249", "Rehabilitation": "311", "Fashion": "410", "Chuunibyou": "267", "Gyaru": "356", "Badminton": "235", "Large Breasts": "137", "Futanari": "188", "Defloration": "129", "Anal Sex": "185", "MILF": "187", "Fellatio": "134", "Tekoki": "317", "Bondage": "246", "Irrumatio": "359", "Circus": "476", "Acting": "548", "LGBTQ Issues": "483", "Ice Skating": "228", "Agender": "334", "Kemonomimi": "254", "Musical": "265", "Mermaid": "558", "Tanks": "174", "Anthology": "471", "No Dialogue": "341", "Superhero": "172", "Lacrosse": "437", "Gambling": "91", "Mahjong": "117", "Dancing": "209", "Bar": "161", "Language Barrier": "516", "Netorare": "124", "Table Tennis": "120", "Werewolf": "534", "Biographical": "239", "Wrestling": "231", "Athletics": "264", "Software Development": "386", "Tentacles": "189", "Public Sex": "127", "Full CGI": "89", "Rakugo": "481", "Scat": "387", "Masturbation": "131", "Facial": "130", "Cunnilingus": "135", "Paizuri": "126", "Nakadashi": "125", "Blackmail": "309", "Volleyball": "116", "Mopeds": "176", "Flash": "242", "Flat Chest": "136", "Threesome": "132", "Sex Toys": "133", "Puppetry": "325", "Fishing": "212", "Incest": "128", "Voyeur": "318", "Shogi": "121", "Prostitution": "190", "Ahegao": "279", "Human Pet": "181", "Ashikoki": "315", "Urination": "180", "Economics": "248", "Ero Guro": "482", "Advertisement": "505", "Stop Motion": "323", "Sumata": "360", "Outdoor": "262", "Netori": "316", "Pregnant": "397", "Autobiographical": "519", "Fitness": "170", "Dark Skin": "335", "POV": "215", "Poker": "183", "Netorase": "280", "Karuta": "182", "Airsoft": "167", "Virginity": "380", "Calligraphy": "204", "Rugby": "221", "Apocalypse": "219", "Body Horror": "333", "Reformation": "407"}